{
	"ModID" : "TTSAssets",
	"ModName" : "Cubiix Project: To The Stars Assets",
	"ModDesc" : "A Collection of assets tailored for Cubiix Project:TTS",
	"ModAuthor" : "Duskitten/Selkspace",
	"Assets" : {
		"Models":{},
		"Override_Binds":{},
		"Maps":{
			"Hexstaria_V2":{
				"Server_Path":"Assets/Maps/Server/hexstaria_v2.tscn",
				"Client_Path":"Assets/Maps/Client/hexstaria_v2.tscn",
				"Name":"Hexstaria",
				"Description":"The home of the Cubiix.",
				"Image_Preview":"Assets/Textures/UI/Map_Previews/Hexstaria_MK2.png",
				"Spawn_Locations":{}
			}
		},
		"Scripts":{
			"Character_Controller":{
				"Path":"Assets/Scripts/Character_Controller.gd"
			},
			"Camera_Controller":{
				"Path":"Assets/Scripts/Camera_Controller.gd"
			},
			"Character_Preview":{
				"Path":"Assets/Scripts/Character_Preview.gd"
			},
			"NPC_Controller":{
				"Path":"Assets/Scripts/NPC_Controller.gd"
			},
			"Network_Character_Controller":{
				"Path":"Assets/Scripts/Client/Network_Character_Controller.gd"
			}
		},
		"Materials":{},
		"Animations":{
			"TTS_Player_Anims":{
				"Path":"Assets/Animations/TTS_Animations.tscn"
			}
		},
		"Dialogue":{
			"Dusk":{
				
			},
			"Nat":{
				
			},
			"Ki":{
				
			},
			"Skim":{
				
			}
		},
		"Devlog_Entries":{
			"V_B.01.00":{
				"Tag":"Log_Entry",
				"Description":"",
				"Author":"Duskitten",
				"Date":"01/15/2025"
			}
		}
	}
}
